s_store_api/__init__.py
s_store_api/admin.py
s_store_api/apps.py
s_store_api/managements.py
s_store_api/models.py
s_store_api/routers.py
s_store_api/serialzers.py
s_store_api/settings.py
s_store_api/urls.py
s_store_api/views.py
s_store_api/fixtures/__init__.py
s_store_api/migrations/0001_initial.py
s_store_api/migrations/0002_auto_20191219_1139.py
s_store_api/migrations/0003_auto_20191219_1149.py
s_store_api/migrations/0004_coin_price.py
s_store_api/migrations/0005_wallet.py
s_store_api/migrations/0006_auto_20191219_1638.py
s_store_api/migrations/0007_store_staff_group.py
s_store_api/migrations/0008_auto_20191220_1123.py
s_store_api/migrations/0009_auto_20191223_1235.py
s_store_api/migrations/0010_cashregister.py
s_store_api/migrations/0011_receipt.py
s_store_api/migrations/__init__.py
s_store_api/permissions/__init__.py
s_store_api/permissions/common.py
s_store_api/permissions/item_permissions.py
s_store_api/permissions/store_permissions.py
s_store_api/tests/__init__.py
s_store_api/tests/utils.py
s_store_api/tests/tests_feature/__init__.py
s_store_api/tests/tests_feature/test_items_get.py
s_store_api/tests/tests_feature/test_items_permission.py
s_store_api/tests/tests_feature/test_manage_stores.py
s_store_api/tests/tests_feature/test_stores_get.py
s_store_api/tests/tests_feature/test_stores_permission.py
s_store_api/tests/tests_feature/test_trade_items.py
s_store_api/utils/__init__.py
s_store_api/utils/auth.py
s_store_api/utils/bag.py
s_store_api/utils/cash_register.py
s_store_api/utils/coin.py
s_store_api/utils/common.py
s_store_api/utils/item.py
s_store_api/utils/price.py
s_store_api/utils/receipt.py
s_store_api/utils/request.py
s_store_api/utils/store.py
s_store_api/utils/views.py
s_store_api/utils/wallet.py
django_s_store_api-1.0.0.dist-info/LICENSE
django_s_store_api-1.0.0.dist-info/METADATA
django_s_store_api-1.0.0.dist-info/WHEEL
django_s_store_api-1.0.0.dist-info/top_level.txt
django_s_store_api-1.0.0.dist-info/RECORD
