Metadata-Version: 2.1
Name: django-s-store-api
Version: 1.0.0
Summary: django-s-store-api is a simple store rest api of django.
Home-page: https://github.com/Saknowman/django-s-store-api
Author: Yuki Sakumoto
Author-email: snowman.sucking@gmail.com
License: MIT
Platform: UNKNOWN
Classifier: Framework :: Django :: 3.0
Classifier: Programming Language :: Python
Classifier: Programming Language :: Python :: 3.7
Classifier: License :: OSI Approved :: MIT License
Requires-Python: >=3.7
Requires-Dist: Django (>=3.0)
Requires-Dist: djangorestframework (==3.11)
